zafiro_api_provider/ZafiroApiProvider.py
zafiro_api_provider/__init__.py
zafiro_api_provider-0.0.4.dist-info/licenses/LICENSE
zafiro_api_provider-0.0.4.dist-info/METADATA
zafiro_api_provider-0.0.4.dist-info/WHEEL
zafiro_api_provider-0.0.4.dist-info/top_level.txt
zafiro_api_provider-0.0.4.dist-info/RECORD
