Metadata-Version: 2.4
Name: zafiro-api-provider
Version: 0.0.4
Summary: Zafiro API Provider
License: MIT
Requires-Python: >=3.8
License-File: LICENSE
Requires-Dist: httpx
Dynamic: license-file
